{
    "backend": "flask",
    "db_name": "",
    "db_pass": "",
    "db_type": "mysql",
    "db_user": "",
    "dbms": "1",
    "description": "generated product",
    "design": "material-kit",
    "docker": "1",
    "err_code": 0,
    "frontend": "",
    "heroku": "0",
    "pattern": "mvc",
    "pro": "0",
    "task_id": "e891e96a-574b-4731-be9a-f21939755cb3",
    "task_info": "Upload Sources [0%] - 348 files",
    "task_output": "e891e96a-574b-4731-be9a-f21939755cb3.zip",
    "task_result": "SUCCESS",
    "task_state": "RUNNING",
    "task_ts_end": "2022-11-10-21-34-46",
    "task_ts_start": "2022-11-10-21-34-44"
}